tensortrade/__about__.py
tensortrade/__init__.py
tensortrade/core/__init__.py
tensortrade/core/base.py
tensortrade/core/clock.py
tensortrade/core/component.py
tensortrade/core/context.py
tensortrade/core/exceptions.py
tensortrade/core/registry.py
tensortrade/env/__init__.py
tensortrade/env/environment.py
tensortrade/env/actions/__init__.py
tensortrade/env/actions/abstract.py
tensortrade/env/actions/bsh.py
tensortrade/env/actions/managed_risk_orders.py
tensortrade/env/actions/simple_orders.py
tensortrade/env/informers/__init__.py
tensortrade/env/informers/abstract.py
tensortrade/env/informers/simple_informer.py
tensortrade/env/mixins/__init__.py
tensortrade/env/mixins/scheme.py
tensortrade/env/observers/__init__.py
tensortrade/env/observers/abstract.py
tensortrade/env/observers/simple.py
tensortrade/env/observers/window.py
tensortrade/env/plotters/__init__.py
tensortrade/env/plotters/abstract.py
tensortrade/env/plotters/matplotlib_trading_chart.py
tensortrade/env/plotters/plotly_trading_chart.py
tensortrade/env/plotters/utils.py
tensortrade/env/rewards/__init__.py
tensortrade/env/rewards/abstract.py
tensortrade/env/rewards/pbr.py
tensortrade/env/rewards/risk_adjusted_returns.py
tensortrade/env/rewards/simple_profit.py
tensortrade/env/stoppers/__init__.py
tensortrade/env/stoppers/abstract.py
tensortrade/env/stoppers/max_loss_stopper.py
tensortrade/env/utils/__init__.py
tensortrade/env/utils/feed_controller.py
tensortrade/env/utils/observation_history.py
tensortrade/feed/__init__.py
tensortrade/feed/api/__init__.py
tensortrade/feed/api/boolean/__init__.py
tensortrade/feed/api/boolean/operations.py
tensortrade/feed/api/float/__init__.py
tensortrade/feed/api/float/accumulators.py
tensortrade/feed/api/float/imputation.py
tensortrade/feed/api/float/operations.py
tensortrade/feed/api/float/ordering.py
tensortrade/feed/api/float/utils.py
tensortrade/feed/api/float/window/__init__.py
tensortrade/feed/api/float/window/ewm.py
tensortrade/feed/api/float/window/expanding.py
tensortrade_ng-2.0.0a2.dist-info/METADATA
tensortrade_ng-2.0.0a2.dist-info/WHEEL
tensortrade_ng-2.0.0a2.dist-info/licenses/LICENSE
tensortrade_ng-2.0.0a2.dist-info/RECORD
