Metadata-Version: 2.3
Name: tensortrade-ng
Version: 2.0.0a2
Summary: TensorTrade-NG: A reinforcement learning library for training, evaluating, and deploying robust trading agents.
Project-URL: Homepage, https://tensortrade-ng.io
Project-URL: Documentation, https://tensortrade-ng.io
Project-URL: Repository, https://github.com/erhardtconsulting/tensortrade-ng.git
Project-URL: Issues, https://github.com/erhardtconsulting/tensortrade-ng/issues
Author-email: Simon Erhardt <simon@erhardt.consulting>, Adam King <adamjking3@gmail.com>, Matthew Brulhardt <mwbrulhardt@gmail.com>
Maintainer-email: Simon Erhardt <simon@erhardt.consulting>
License: 
License-File: LICENSE
Keywords: ai,artificial intelligence,finance,machine learning,tensortrade,trading
Classifier: Development Status :: 5 - Production/Stable
Classifier: Intended Audience :: Developers
Classifier: Intended Audience :: Education
Classifier: Intended Audience :: Financial and Insurance Industry
Classifier: Intended Audience :: Information Technology
Classifier: Intended Audience :: Science/Research
Classifier: License :: OSI Approved :: Apache Software License
Classifier: Natural Language :: English
Classifier: Operating System :: OS Independent
Classifier: Programming Language :: Python :: 3.12
Classifier: Topic :: Office/Business :: Financial
Classifier: Topic :: Office/Business :: Financial :: Investment
Classifier: Topic :: Scientific/Engineering :: Artificial Intelligence
Classifier: Topic :: Scientific/Engineering :: Information Analysis
Classifier: Topic :: Software Development :: Libraries
Classifier: Topic :: Software Development :: Libraries :: Python Modules
Classifier: Topic :: System :: Distributed Computing
Requires-Python: >=3.10
Requires-Dist: deprecated>=1.2.14
Requires-Dist: gymnasium>=0.29.1
Requires-Dist: matplotlib>=3.9.2
Requires-Dist: numpy>=1.26.4
Requires-Dist: pandas>=2.2.2
Requires-Dist: plotly>=5.23.0
Requires-Dist: pyyaml>=6.0.2
Provides-Extra: dev
Requires-Dist: hatch-vcs>=0.4.0; extra == 'dev'
Requires-Dist: hatch>=1.12.0; extra == 'dev'
Requires-Dist: ipykernel>=6.29.5; extra == 'dev'
Requires-Dist: ipython>=8.26.0; extra == 'dev'
Requires-Dist: ipywidgets>=8.1.3; extra == 'dev'
Requires-Dist: nbsphinx-link>=1.3.0; extra == 'dev'
Requires-Dist: nbsphinx>=0.9.5; extra == 'dev'
Requires-Dist: pytest-cov>=5.0.0; extra == 'dev'
Requires-Dist: pytest>=5.1.1; extra == 'dev'
Requires-Dist: recommonmark>=0.7.1; extra == 'dev'
Requires-Dist: scikit-learn>=1.5.1; extra == 'dev'
Requires-Dist: sphinx-autobuild>=2024.4.16; extra == 'dev'
Requires-Dist: sphinx-markdown-tables>=0.0.17; extra == 'dev'
Requires-Dist: sphinx-rtd-theme>=2.0.0; extra == 'dev'
Requires-Dist: sphinx>=7.4.7; extra == 'dev'
Requires-Dist: sphinxcontrib-apidoc>=0.5.0; extra == 'dev'
Requires-Dist: stable-baselines3>=2.3.2; extra == 'dev'
Requires-Dist: ta>=0.11.0; extra == 'dev'
Requires-Dist: ta>=0.4.7; extra == 'dev'
Requires-Dist: tox>=4.18.0; extra == 'dev'
Provides-Extra: doc
Requires-Dist: ipython>=8.26.0; extra == 'doc'
Requires-Dist: nbsphinx-link>=1.3.0; extra == 'doc'
Requires-Dist: nbsphinx>=0.9.5; extra == 'doc'
Requires-Dist: recommonmark>=0.7.1; extra == 'doc'
Requires-Dist: sphinx-autobuild>=2024.4.16; extra == 'doc'
Requires-Dist: sphinx-markdown-tables>=0.0.17; extra == 'doc'
Requires-Dist: sphinx-rtd-theme>=2.0.0; extra == 'doc'
Requires-Dist: sphinx>=7.4.7; extra == 'doc'
Requires-Dist: sphinxcontrib-apidoc>=0.5.0; extra == 'doc'
Provides-Extra: jlab
Requires-Dist: ipykernel>=6.29.5; extra == 'jlab'
Requires-Dist: ipython>=8.26.0; extra == 'jlab'
Requires-Dist: ipywidgets>=8.1.3; extra == 'jlab'
Requires-Dist: scikit-learn>=1.5.1; extra == 'jlab'
Requires-Dist: stable-baselines3>=2.3.2; extra == 'jlab'
Requires-Dist: ta>=0.11.0; extra == 'jlab'
Provides-Extra: test
Requires-Dist: ipython>=8.26.0; extra == 'test'
Requires-Dist: pytest-cov>=5.0.0; extra == 'test'
Requires-Dist: pytest>=5.1.1; extra == 'test'
Requires-Dist: ta>=0.4.7; extra == 'test'
